{"id":35984,"path":"Assets/Prefabs/TileSlot.prefab","assetBundleId":-1,"components":[{"type":1,"id":36562,"data":[1,0,0,1,1,1,0,0,0,1]},{"type":2,"id":36566,"enabled":1,"class":8,"data":[0,null,null]}],"children":[{"id":36594,"path":"Assets/Prefabs/TileSlot.prefab","assetBundleId":-1,"components":[{"type":1,"id":36592,"data":[0,0,0,1,1,1,0,0,0,1]},{"type":4,"id":36596,"data":[1,6,58,[6,58],0,0,0,0,-1,-1,1,1,0,0,1,1,1,1,1,1,7,33582,0,0,0,1,1,0,0.5,0,0]}],"children":[],"data":["TempBackground",0,1,0,0]}],"data":["TileSlot",0,1,0,0]}